cre_cfuncs.cp39-win_amd64.pyd
cre/__init__.py
cre/attr_filter.py
cre/caching.py
cre/change_event.py
cre/conditions.py
cre/console_script.py
cre/context.py
cre/core.py
cre/default_funcs.py
cre/dynamic_exec.py
cre/fact.py
cre/fact_intrinsics.py
cre/func.py
cre/gval.py
cre/hashing.py
cre/make_source.py
cre/matching.py
cre/memset.py
cre/obj.py
cre/rule.py
cre/sc_planner.py
cre/structref.py
cre/tuple_fact.py
cre/type_conv.py
cre/utils.py
cre/var.py
cre/vector.py
cre/version.py
cre/cfuncs/__init__.py
cre/cfuncs/cre_cfuncs.c
cre/transform/__init__.py
cre/transform/enumerizer.py
cre/transform/feature_applier.py
cre/transform/flattener.py
cre/transform/incr_processor.py
cre/transform/memset_builder.py
cre/transform/relative_encoder.py
cre/transform/vectorizer.py
cre_caching/__init__.py
cre_caching/caching.py
cre-0.4.4.dist-info/LICENSE.txt
cre-0.4.4.dist-info/METADATA
cre-0.4.4.dist-info/WHEEL
cre-0.4.4.dist-info/entry_points.txt
cre-0.4.4.dist-info/top_level.txt
cre-0.4.4.dist-info/RECORD
